retrodetect/__init__.py
retrodetect/detect.py
retrodetect/image_processing/__init__.py
retrodetect/image_processing/image_processing.py
retrodetect/image_processing/normxcorr2.py
retrodetect-0.0.2.dist-info/LICENSE
retrodetect-0.0.2.dist-info/METADATA
retrodetect-0.0.2.dist-info/WHEEL
retrodetect-0.0.2.dist-info/top_level.txt
retrodetect-0.0.2.dist-info/RECORD
