Metadata-Version: 2.1
Name: retrodetect
Version: 0.0.2
Summary: Finds retroreflectors in a pair of images
Author-email: Mike Smith <m.t.smith@sheffield.ac.uk>
Maintainer-email: Mike Smith <m.t.smith@sheffield.ac.uk>
License: 1 User: Fair Source License, version 0.9
Project-URL: Homepage, https://pypi.org/project/retrodetect/
Project-URL: Repository, https://github.com/SheffieldMLtracking/retrodetect
Keywords: bee,retroreflectors,small animals,tracking
Classifier: Development Status :: 4 - Beta
Classifier: Programming Language :: Python :: 3
Classifier: License :: OSI Approved :: MIT License
Classifier: Operating System :: OS Independent
Requires-Python: >=3.8
License-File: LICENSE
Requires-Dist: numpy
Requires-Dist: scipy
Provides-Extra: test
Requires-Dist: flake8 ; extra == 'test'
Requires-Dist: pytest ; extra == 'test'
Requires-Dist: opencv-python ; extra == 'test'
Requires-Dist: pandas ; extra == 'test'
